uuid_filelock/__init__.py
uuid_filelock-1.4.dist-info/METADATA
uuid_filelock-1.4.dist-info/WHEEL
uuid_filelock-1.4.dist-info/top_level.txt
uuid_filelock-1.4.dist-info/RECORD
