Metadata-Version: 2.1
Name: uuid-filelock
Version: 1.4
Summary: A simple UUID-based file lock implementation for Python.
Home-page: https://github.com/z3rone-org/uuid_filelock
Author: Falk B. Schimweg
Author-email: git@falk.schimweg.de
License: MIT
Classifier: Programming Language :: Python :: 3
Classifier: License :: OSI Approved :: MIT License
Classifier: Operating System :: OS Independent
Requires-Python: >=3.7
Provides-Extra: dev
Requires-Dist: pytest; extra == "dev"
